moconf/__init__.py
moconf/appliance.py
moconf/infra.py
moconf-0.0.35.dist-info/LICENSE
moconf-0.0.35.dist-info/METADATA
moconf-0.0.35.dist-info/WHEEL
moconf-0.0.35.dist-info/top_level.txt
moconf-0.0.35.dist-info/RECORD
