Metadata-Version: 2.1
Name: moconf
Version: 0.0.35
Summary: moconf is a package for configuring a Morpheus appliance.
Home-page: https://github.com/morpheus-training/moconf
Author: Sean Jabro
Author-email: sjabro@morpheusdata.com
License: Apache 2.0
Platform: UNKNOWN
License-File: LICENSE
Requires-Dist: requests (>=2.21.0)
Requires-Dist: urllib3
